elpepetst/assets/static.json
elpepetst/main.py
elpepetst-0.0.3.dist-info/METADATA
elpepetst-0.0.3.dist-info/WHEEL
elpepetst-0.0.3.dist-info/entry_points.txt
elpepetst-0.0.3.dist-info/RECORD
