Metadata-Version: 2.1
Name: elpepetst
Version: 0.0.3
Summary: Elpepe test package
License: ISC
Author: atlasfoo
Requires-Python: >=3.10,<4.0
Classifier: License :: OSI Approved
Classifier: Programming Language :: Python :: 3
Classifier: Programming Language :: Python :: 3.10
Classifier: Programming Language :: Python :: 3.11
Requires-Dist: requests (>=2.31.0,<3.0.0)
